tpe/__init__.py
tpe/optimizer/__init__.py
tpe/optimizer/base_optimizer.py
tpe/optimizer/random_search.py
tpe/optimizer/tpe.py
tpe/utils/constants.py
tpe/utils/utils.py
tpe-0.0.8.dist-info/LICENSE
tpe-0.0.8.dist-info/METADATA
tpe-0.0.8.dist-info/WHEEL
tpe-0.0.8.dist-info/top_level.txt
tpe-0.0.8.dist-info/RECORD
