Metadata-Version: 2.1
Name: tpe
Version: 0.0.8
Summary: UNKNOWN
Home-page: https://github.com/nabenabe0928/tpe
Author: nabenabe0928
Author-email: shuhei.watanabe.utokyo@gmail.com
License: UNKNOWN
Platform: Linux
Requires-Python: >=3.8
Requires-Dist: numpy
Requires-Dist: ConfigSpace
Requires-Dist: parzen-estimator
